asincRStrigger.v
module asincRStrigger(
    input s,
    input r,
    output q,
    output q_n
);
    assign q = ~ (r | q_n);
    assign q_n = ~ (s | q);
endmodule

d_latch.v
module d_latch  (
    input clk,
    input d,
    output q,
    output q_n
);
    wire r = ~d & clk;
    wire s = d & clk;
    asincRStrigger sr_latch (s, r, q, q_n);
endmodule

testbench.v
`timescale 1 ns / 100 ps
module testbench;
reg s, r;
wire q, q_n;
d_latch d_latch (s, r, q, q_n);
initial $dumpvars;
initial
begin
$monitor ("%0d s %b r %b q %b q_n %b", $time, s, r, q, q_n);
# 10; s = 0; r = 0;
# 10; s = 1; r = 0;
# 10; s = 0; r = 0;
# 10; s = 0; r = 1;
# 10; s = 0; r = 0;
# 10; s = 1; r = 1;
# 10; s = 0; r = 0;
# 10; s = 0; r = 0;
# 10;
$finish;
end
endmodule

dump.vcd
$date
	Thu Jul 24 15:25:48 2025
$end
$version
	Icarus Verilog
$end
$timescale
	100ps
$end
$scope module testbench $end
$var wire 1 ! q $end
$var wire 1 " q_n $end
$var reg 1 # r $end
$var reg 1 $ s $end
$scope module d_latch $end
$var wire 1 % clk $end
$var wire 1 & d $end
$var wire 1 ! q $end
$var wire 1 " q_n $end
$var wire 1 ' r $end
$var wire 1 ( s $end
$scope module sr_latch $end
$var wire 1 ! q $end
$var wire 1 " q_n $end
$var wire 1 ' r $end
$var wire 1 ( s $end
$upscope $end
$upscope $end
$upscope $end
$enddefinitions $end
#0
$dumpvars
x(
x'
x&
x%
x$
x#
x"
x!
$end
#100
0'
0(
0#
0&
0$
0%
#200
1"
0!
1'
1$
1%
#300
0'
0$
0%
#400
1#
1&
#500
0#
0&
#600
1!
0"
0'
1(
1#
1&
1$
1%
#700
0(
0#
0&
0$
0%
